aequilibrae-1.5.0.dist-info/RECORD
aequilibrae-1.5.0.dist-info/WHEEL
aequilibrae-1.5.0.dist-info/top_level.txt
aequilibrae-1.5.0.dist-info/METADATA
aequilibrae/parameters.yml
aequilibrae/log.py
aequilibrae/__init__.py
aequilibrae/context.py
aequilibrae/parameters.py
aequilibrae/distribution/gravity_calibration.py
aequilibrae/distribution/ipf.py
aequilibrae/distribution/setup_ipf.py
aequilibrae/distribution/__init__.py
aequilibrae/distribution/gravity_application.py
aequilibrae/distribution/ipf_core.cpython-312-darwin.so
aequilibrae/distribution/synthetic_gravity_model.py
aequilibrae/distribution/cython/ipf_core.pyx
aequilibrae/distribution/cython/ipf_core.cpp
aequilibrae/paths/optimal_strategies.py
aequilibrae/paths/multi_threaded_paths.py
aequilibrae/paths/route_choice.py
aequilibrae/paths/connectivity_analysis.py
aequilibrae/paths/vdf.py
aequilibrae/paths/linear_approximation.py
aequilibrae/paths/all_or_nothing.py
aequilibrae/paths/graph.py
aequilibrae/paths/assignment_paths.py
aequilibrae/paths/__init__.py
aequilibrae/paths/network_skimming.py
aequilibrae/paths/traffic_assignment.py
aequilibrae/paths/sub_area.py
aequilibrae/paths/public_transport.cpython-312-darwin.so
aequilibrae/paths/multi_threaded_skimming.py
aequilibrae/paths/graph_building.cpython-312-darwin.so
aequilibrae/paths/setup_assignment.py
aequilibrae/paths/traffic_class.py
aequilibrae/paths/AoN.cpython-312-darwin.so
aequilibrae/paths/multi_threaded_aon.py
aequilibrae/paths/cython/path_file_saving.pyx
aequilibrae/paths/cython/route_choice_set_results.cpp
aequilibrae/paths/cython/graph_building.cpp
aequilibrae/paths/cython/route_choice_set_results.pxd
aequilibrae/paths/cython/route_choice_set_results.cpython-312-darwin.so
aequilibrae/paths/cython/route_choice_set.cpython-312-darwin.so
aequilibrae/paths/cython/public_transport.cpp
aequilibrae/paths/cython/parallel_numpy.pyx
aequilibrae/paths/cython/bpr.pyx
aequilibrae/paths/cython/route_choice_link_loading_results.pyx
aequilibrae/paths/cython/pq_4ary_heap.pyx
aequilibrae/paths/cython/route_choice_set.pxd
