Metadata-Version: 2.4
Name: aequilibrae
Version: 1.5.0
Summary: A package for transportation modeling
Author-email: Pedro Camargo <pedro@outerloop.io>
Maintainer: AequilibraE contributors
License: MIT License (with added clause)
Classifier: Development Status :: 5 - Production/Stable
Classifier: Intended Audience :: Developers
Classifier: Intended Audience :: Science/Research
Classifier: Intended Audience :: End Users/Desktop
Classifier: Intended Audience :: Other Audience
Classifier: Operating System :: OS Independent
Classifier: Programming Language :: Python
Classifier: Programming Language :: Python :: 3
Classifier: Programming Language :: Python :: 3 :: Only
Classifier: Programming Language :: Python :: 3.9
Classifier: Programming Language :: Python :: 3.10
Classifier: Programming Language :: Python :: 3.11
Classifier: Programming Language :: Python :: 3.12
Classifier: Programming Language :: Python :: 3.13
Classifier: Topic :: Scientific/Engineering
Requires-Python: >=3.9
Requires-Dist: numpy<1.99; python_version <= "3.10"
Requires-Dist: numpy>=2.0; python_version >= "3.11"
Requires-Dist: scipy>=1.4
Requires-Dist: pyaml
Requires-Dist: requests
Requires-Dist: pandas
Requires-Dist: pyproj
Requires-Dist: rtree
Requires-Dist: pyarrow
Requires-Dist: openmatrix
Requires-Dist: geopandas
Requires-Dist: tqdm
Provides-Extra: docs
Requires-Dist: enum34; extra == "docs"
Requires-Dist: Sphinx; extra == "docs"
Requires-Dist: pydata-sphinx-theme; extra == "docs"
Requires-Dist: sphinx_autodoc_annotation; extra == "docs"
Requires-Dist: matplotlib; extra == "docs"
Requires-Dist: folium; extra == "docs"
Requires-Dist: mapclassify; extra == "docs"
Requires-Dist: sphinx-gallery; extra == "docs"
Requires-Dist: sphinx-copybutton; extra == "docs"
Requires-Dist: sphinx-design; extra == "docs"
Requires-Dist: sphinx-git; extra == "docs"
Requires-Dist: nbconvert; extra == "docs"
Requires-Dist: sphinx-tabs; extra == "docs"
Requires-Dist: sphinx-subfigure; extra == "docs"
Provides-Extra: tests
Requires-Dist: setuptools; extra == "tests"
Requires-Dist: codecov; extra == "tests"
Requires-Dist: pytest; extra == "tests"
Requires-Dist: pytest-xdist; extra == "tests"
Requires-Dist: pytest-cov; extra == "tests"
Requires-Dist: pytest-subtests; extra == "tests"
Requires-Dist: pytest-random-order; extra == "tests"
Requires-Dist: coveralls; extra == "tests"
Requires-Dist: ruff==0.9.10; extra == "tests"
Requires-Dist: black==25.1.0; extra == "tests"
Requires-Dist: wheel; extra == "tests"
Provides-Extra: build
Requires-Dist: setuptools; extra == "build"
Requires-Dist: numpy<1.99; python_version <= "3.10" and extra == "build"
Requires-Dist: numpy>=2.0; python_version >= "3.11" and extra == "build"
Requires-Dist: cython; extra == "build"
Requires-Dist: wheel; extra == "build"
Provides-Extra: dev
Requires-Dist: aequilibrae[build,docs,tests]; extra == "dev"
